README.rst
setup.py
django_sendgrid_events.egg-info/PKG-INFO
django_sendgrid_events.egg-info/SOURCES.txt
django_sendgrid_events.egg-info/dependency_links.txt
django_sendgrid_events.egg-info/not-zip-safe
django_sendgrid_events.egg-info/top_level.txt
sendgrid_events/__init__.py
sendgrid_events/admin.py
sendgrid_events/models.py
sendgrid_events/signals.py
sendgrid_events/urls.py
sendgrid_events/views.py