Metadata-Version: 1.1
Name: django-sendgrid-events
Version: 1.2
Summary: a django app for handling sendgrid batch events
Home-page: https://github.com/eldarion/django-sendgrid-events
Author: Patrick Altman
Author-email: paltman@eldarion.com
License: BSD
Platform: UNKNOWN
Classifier: Development Status :: 3 - Alpha
Classifier: Environment :: Web Environment
Classifier: Intended Audience :: Developers
Classifier: License :: OSI Approved :: BSD License
Classifier: Operating System :: OS Independent
Classifier: Programming Language :: Python
Classifier: Framework :: Django
